{"character_id":"LordMayor_H8","co_present":{"full":{"size":23,"density":0.762846,"top_ties":[["Garter_H8",2],["LADIES_H8",2],["Norfolk_H8",2],["Suffolk_H8",2],["ALDERMEN_H8",1]]},"cumulative_scene":[{"time_index":12,"size":17,"density":1.0,"top_ties":[["Anne_H8",1],["BishopOfLondon_H8",1],["CHORISTERS_H8",1],["Chancellor_H8",1],["Dorset_H8",1]],"new_ties":[["Anne_H8",1],["BishopOfLondon_H8",1],["CHORISTERS_H8",1],["Chancellor_H8",1],["Dorset_H8",1],["GENTLEMEN.1_H8",1],["GENTLEMEN.2_H8",1],["GENTLEMEN.3_H8",1],["Gardiner_H8",1],["Garter_H8",1],["JUDGES_H8",1],["LADIES_H8",1],["LORDS.CINQUEPORTS_H8",1],["Norfolk_H8",1],["Suffolk_H8",1],["Surrey_H8",1]],"lost_ties":[]},{"time_index":13,"size":17,"density":1.0,"top_ties":[["Anne_H8",1],["BishopOfLondon_H8",1],["CHORISTERS_H8",1],["Chancellor_H8",1],["Dorset_H8",1]],"new_ties":[],"lost_ties":[]},{"time_index":14,"size":17,"density":1.0,"top_ties":[["Anne_H8",1],["BishopOfLondon_H8",1],["CHORISTERS_H8",1],["Chancellor_H8",1],["Dorset_H8",1]],"new_ties":[],"lost_ties":[]},{"time_index":15,"size":17,"density":1.0,"top_ties":[["Anne_H8",1],["BishopOfLondon_H8",1],["CHORISTERS_H8",1],["Chancellor_H8",1],["Dorset_H8",1]],"new_ties":[],"lost_ties":[]},{"time_index":16,"size":17,"density":1.0,"top_ties":[["Anne_H8",1],["BishopOfLondon_H8",1],["CHORISTERS_H8",1],["Chancellor_H8",1],["Dorset_H8",1]],"new_ties":[],"lost_ties":[]},{"time_index":17,"size":23,"density":0.762846,"top_ties":[["Garter_H8",2],["LADIES_H8",2],["Norfolk_H8",2],["Suffolk_H8",2],["ALDERMEN_H8",1]],"new_ties":[["ALDERMEN_H8",1],["Cranmer_H8",1],["ElizabethI.Infant_H8",1],["GUARDS_H8",1],["HenryVIII_H8",1],["LORDS_H8",1]],"lost_ties":[]},{"time_index":18,"size":23,"density":0.762846,"top_ties":[["Garter_H8",2],["LADIES_H8",2],["Norfolk_H8",2],["Suffolk_H8",2],["ALDERMEN_H8",1]],"new_ties":[],"lost_ties":[]}],"cumulative_act":[{"time_index":4,"size":17,"density":1.0,"top_ties":[["Anne_H8",1],["BishopOfLondon_H8",1],["CHORISTERS_H8",1],["Chancellor_H8",1],["Dorset_H8",1]],"new_ties":[["Anne_H8",1],["BishopOfLondon_H8",1],["CHORISTERS_H8",1],["Chancellor_H8",1],["Dorset_H8",1],["GENTLEMEN.1_H8",1],["GENTLEMEN.2_H8",1],["GENTLEMEN.3_H8",1],["Gardiner_H8",1],["Garter_H8",1],["JUDGES_H8",1],["LADIES_H8",1],["LORDS.CINQUEPORTS_H8",1],["Norfolk_H8",1],["Suffolk_H8",1],["Surrey_H8",1]],"lost_ties":[]},{"time_index":5,"size":23,"density":0.762846,"top_ties":[["Garter_H8",2],["LADIES_H8",2],["Norfolk_H8",2],["Suffolk_H8",2],["ALDERMEN_H8",1]],"new_ties":[["ALDERMEN_H8",1],["Cranmer_H8",1],["ElizabethI.Infant_H8",1],["GUARDS_H8",1],["HenryVIII_H8",1],["LORDS_H8",1]],"lost_ties":[]}],"sliding_window_5":[{"time_index":12,"size":17,"density":1.0,"top_ties":[["Anne_H8",1],["BishopOfLondon_H8",1],["CHORISTERS_H8",1],["Chancellor_H8",1],["Dorset_H8",1]],"new_ties":[["Anne_H8",1],["BishopOfLondon_H8",1],["CHORISTERS_H8",1],["Chancellor_H8",1],["Dorset_H8",1],["GENTLEMEN.1_H8",1],["GENTLEMEN.2_H8",1],["GENTLEMEN.3_H8",1],["Gardiner_H8",1],["Garter_H8",1],["JUDGES_H8",1],["LADIES_H8",1],["LORDS.CINQUEPORTS_H8",1],["Norfolk_H8",1],["Suffolk_H8",1],["Surrey_H8",1]],"lost_ties":[]},{"time_index":13,"size":17,"density":1.0,"top_ties":[["Anne_H8",1],["BishopOfLondon_H8",1],["CHORISTERS_H8",1],["Chancellor_H8",1],["Dorset_H8",1]],"new_ties":[],"lost_ties":[]},{"time_index":14,"size":17,"density":1.0,"top_ties":[["Anne_H8",1],["BishopOfLondon_H8",1],["CHORISTERS_H8",1],["Chancellor_H8",1],["Dorset_H8",1]],"new_ties":[],"lost_ties":[]},{"time_index":15,"size":17,"density":1.0,"top_ties":[["Anne_H8",1],["BishopOfLondon_H8",1],["CHORISTERS_H8",1],["Chancellor_H8",1],["Dorset_H8",1]],"new_ties":[],"lost_ties":[]},{"time_index":16,"size":17,"density":1.0,"top_ties":[["Anne_H8",1],["BishopOfLondon_H8",1],["CHORISTERS_H8",1],["Chancellor_H8",1],["Dorset_H8",1]],"new_ties":[],"lost_ties":[]},{"time_index":17,"size":11,"density":1.0,"top_ties":[["ALDERMEN_H8",1],["Cranmer_H8",1],["ElizabethI.Infant_H8",1],["GUARDS_H8",1],["Garter_H8",1]],"new_ties":[["ALDERMEN_H8",1],["Cranmer_H8",1],["ElizabethI.Infant_H8",1],["GUARDS_H8",1],["HenryVIII_H8",1],["LORDS_H8",1]],"lost_ties":[["Anne_H8",1],["BishopOfLondon_H8",1],["CHORISTERS_H8",1],["Chancellor_H8",1],["Dorset_H8",1],["GENTLEMEN.1_H8",1],["GENTLEMEN.2_H8",1],["GENTLEMEN.3_H8",1],["Gardiner_H8",1],["JUDGES_H8",1],["LORDS.CINQUEPORTS_H8",1],["Surrey_H8",1]]},{"time_index":18,"size":11,"density":1.0,"top_ties":[["ALDERMEN_H8",1],["Cranmer_H8",1],["ElizabethI.Infant_H8",1],["GUARDS_H8",1],["Garter_H8",1]],"new_ties":[],"lost_ties":[]}]}}